Instruction Fetch/IF_Stage_Reg.v
module IF_Stage_Reg (clk, rst, freeze, flush, PC_in, Instruction_in, PC, Instruction);

    input clk, rst, freeze, flush;
    input [31:0] PC_in, Instruction_in; 
    output reg [31:0] PC, Instruction;
  
    always @ (posedge clk, posedge rst) begin
        if (rst) begin
        PC <= 32'b00000000000000000000000000000000;
        Instruction <= 32'b11100000000000000000000000000000;
        end 
        else if (!freeze) begin
            if (flush) begin
                PC <= 32'b00000000000000000000000000000000;
                Instruction <= 32'b11100000000000000000000000000000;
            end 
        else begin 
            Instruction <= Instruction_in; PC <= PC_in; end
        end
    end
endmodule

ARM/Instruction_memory.v

module Instruction_memory(input clk, rst, input [31:0]PC, output reg [31:0]Instruction);

    reg [7:0] _Instruction[191:0];

    always @ (*) begin
        if (rst) begin
            {_Instruction[3],  _Instruction[2],  _Instruction[1],  _Instruction[0]} =  32'b1110_00_1_1101_0_0000_0000_000000010100;
            {_Instruction[7],  _Instruction[6],  _Instruction[5],  _Instruction[4]} =  32'b1110_00_1_1101_0_0000_0001_101000000001;
            {_Instruction[11],  _Instruction[10],  _Instruction[9], _Instruction[8]} = 32'b1110_00_1_1101_0_0000_0010_000100000011;
            {_Instruction[15], _Instruction[14], _Instruction[13], _Instruction[12]} = 32'b1110_00_0_0100_1_0010_0011_000000000010;
            {_Instruction[19], _Instruction[18], _Instruction[17], _Instruction[16]} = 32'b1110_00_0_0101_0_0000_0100_000000000000;
            {_Instruction[23], _Instruction[22], _Instruction[21], _Instruction[20]} = 32'b1110_00_0_0010_0_0100_0101_000100000100;
            {_Instruction[27], _Instruction[26], _Instruction[25], _Instruction[24]} = 32'b1110_00_0_0110_0_0000_0110_000010100000;
            {_Instruction[31], _Instruction[30], _Instruction[29], _Instruction[28]} = 32'b1110_00_0_1100_0_0101_0111_000101000010;
            {_Instruction[35], _Instruction[34], _Instruction[33], _Instruction[32]} = 32'b1110_00_0_0000_0_0111_1000_000000000011;
            {_Instruction[39], _Instruction[38], _Instruction[37], _Instruction[36]} = 32'b1110_00_0_1111_0_0000_1001_000000000110;
            {_Instruction[43], _Instruction[42], _Instruction[41], _Instruction[40]} = 32'b1110_00_0_0001_0_0100_1010_000000000101;
            {_Instruction[47], _Instruction[46], _Instruction[45], _Instruction[44]} = 32'b1110_00_0_1010_1_1000_0000_000000000110;
            {_Instruction[51], _Instruction[50], _Instruction[49], _Instruction[48]} = 32'b0001_00_0_0100_0_0001_0001_000000000001;
            {_Instruction[55], _Instruction[54], _Instruction[53], _Instruction[52]} = 32'b1110_00_0_1000_1_1001_0000_000000001000;
            {_Instruction[59], _Instruction[58], _Instruction[57], _Instruction[56]} = 32'b0000_00_0_0100_0_0010_0010_000000000010;
            {_Instruction[63], _Instruction[62], _Instruction[61], _Instruction[60]} = 32'b1110_00_1_1101_0_0000_0000_101100000001;
            {_Instruction[67], _Instruction[66], _Instruction[65], _Instruction[64]} = 32'b1110_01_0_0100_0_0000_0001_000000000000;
            {_Instruction[71], _Instruction[70], _Instruction[69], _Instruction[68]} = 32'b1110_01_0_0100_1_0000_1011_000000000000;
            {_Instruction[75], _Instruction[74], _Instruction[73], _Instruction[72]} = 32'b1110_01_0_0100_0_0000_0010_000000000100;
            {_Instruction[79], _Instruction[78], _Instruction[77], _Instruction[76]} = 32'b1110_01_0_0100_0_0000_0011_000000001000;
            {_Instruction[83], _Instruction[82], _Instruction[81], _Instruction[80]} = 32'b1110_01_0_0100_0_0000_0100_000000001101;
            {_Instruction[87], _Instruction[86], _Instruction[85], _Instruction[84]} = 32'b1110_01_0_0100_0_0000_0101_000000010000;
            {_Instruction[91], _Instruction[90], _Instruction[89], _Instruction[88]} = 32'b1110_01_0_0100_0_0000_0110_000000010100;
            {_Instruction[95], _Instruction[94], _Instruction[93], _Instruction[92]} = 32'b1110_01_0_0100_1_0000_1010_000000000100;
            {_Instruction[99],  _Instruction[98],  _Instruction[97], _Instruction[96]} = 32'b1110_01_0_0100_0_0000_0111_000000011000;
            {_Instruction[103], _Instruction[102], _Instruction[101], _Instruction[100]} = 32'b1110_00_1_1101_0_0000_0001_000000000100;
            {_Instruction[107], _Instruction[106], _Instruction[105], _Instruction[104]} = 32'b1110_00_1_1101_0_0000_0010_000000000000;
            {_Instruction[111], _Instruction[110], _Instruction[109], _Instruction[108]} = 32'b1110_00_1_1101_0_0000_0011_000000000000;
            {_Instruction[115], _Instruction[114], _Instruction[113], _Instruction[112]} = 32'b1110_00_0_0100_0_0000_0100_000100000011;
            {_Instruction[119], _Instruction[118], _Instruction[117], _Instruction[116]} = 32'b1110_01_0_0100_1_0100_0101_000000000000;
            {_Instruction[123], _Instruction[122], _Instruction[121], _Instruction[120]} = 32'b1110_01_0_0100_1_0100_0110_000000000100;
            {_Instruction[127], _Instruction[126], _Instruction[125], _Instruction[124]} = 32'b1110_00_0_1010_1_0101_0000_000000000110;
            {_Instruction[131], _Instruction[130], _Instruction[129], _Instruction[128]} = 32'b1100_01_0_0100_0_0100_0110_000000000000;
            {_Instruction[135], _Instruction[134], _Instruction[133], _Instruction[132]} = 32'b1100_01_0_0100_0_0100_0101_000000000100;
            {_Instruction[139], _Instruction[138], _Instruction[137], _Instruction[136]} = 32'b1110_00_1_0100_0_0011_0011_000000000001;
            {_Instruction[143], _Instruction[142], _Instruction[141], _Instruction[140]} = 32'b1110_00_1_1010_1_0011_0000_000000000011;
            {_Instruction[147], _Instruction[146], _Instruction[145], _Instruction[144]} = 32'b1011_10_1_0_111111111111111111110111;
            {_Instruction[151], _Instruction[150], _Instruction[149], _Instruction[148]} = 32'b1110_00_1_0100_0_0010_0010_000000000001;
            {_Instruction[155], _Instruction[154], _Instruction[153], _Instruction[152]} = 32'b1110_00_0_1010_1_0010_0000_000000000001;
            {_Instruction[159], _Instruction[158], _Instruction[157], _Instruction[156]} = 32'b1011_10_1_0_111111111111111111110011;
            {_Instruction[163], _Instruction[162], _Instruction[161], _Instruction[160]} = 32'b1110_01_0_0100_1_0000_0001_000000000000; 
            {_Instruction[167], _Instruction[166], _Instruction[165], _Instruction[164]} = 32'b1110_01_0_0100_1_0000_0010_000000000100;
            {_Instruction[171], _Instruction[170], _Instruction[169], _Instruction[168]} = 32'b1110_01_0_0100_1_0000_0011_000000001000;
            {_Instruction[175], _Instruction[174], _Instruction[173], _Instruction[172]} = 32'b1110_01_0_0100_1_0000_0100_000000001100;
            {_Instruction[179], _Instruction[178], _Instruction[177], _Instruction[176]} = 32'b1110_01_0_0100_1_0000_0101_000000010000;
            {_Instruction[183], _Instruction[182], _Instruction[181], _Instruction[180]} = 32'b1110_01_0_0100_1_0000_0110_000000010100;
            {_Instruction[187], _Instruction[186], _Instruction[185], _Instruction[184]} = 32'b1110_10_1_0_111111111111111111111111;
            {_Instruction[191], _Instruction[190], _Instruction[189], _Instruction[188]} = 32'b0;
        end else Instruction <= {_Instruction[PC + 2'b11], _Instruction[PC + 2'b10], _Instruction[PC + 2'b01], _Instruction[PC + 2'b00]};  
  end
    
endmodule

Instruction Fetch/adder.v

module adder(x0, x1, y);
	input [31:0] x0, x1;
	output [31:0] y;
	
	assign y = x0 + x1;
endmodule

Instruction Fetch/PC.v
module PC(clk, rst, freeze, in, out);
input clk, rst, freeze;
input [31:0] in;
output reg [31:0] out;
  always @ (posedge clk, posedge rst) begin
    if (rst) out <= 32'b0;
    else begin
      if (freeze) out <= out;
      else out <= in;
    end
  end

endmodule

// clk = 50MHZ
// rst negative

Instruction Fetch/IF_Stage.v
`include "adder.v"
`include "Instruction_memory.v"
`include "PC.v"
module IF_Stage(clk, rst, freeze, Branch_Tacken, Branch_Address, Instruction, pc);
    input clk, rst, freeze, Branch_Tacken;
    input [31:0] Branch_Address;
    output [31:0]  Instruction;
    output [31:0] pc;
    wire [31:0] pc_out, adder_o;
    reg [31:0] pc_in;
    wire [31:0] PC_in;
	
    always@(posedge clk)
	    pc_in = Branch_Tacken ? adder_o : Branch_Address;
    assign PC_in = pc_in;
    // mux2to1 mux_IF(.sel(Branch_Tacken), .x0(Branch_Address), .x1(adder_o), .y(pc_in));
    PC pc_instance(.clk(clk), .rst(rst), .freeze(freeze), .in(PC_in), .out(pc_out));
    // assign adder_o = pc_out;
    // assign Instruction = pc_out;
    adder adder_IF(.x0(pc_out), .x1(32'd4), .y(adder_o));
    Instruction_memory IM(.clk(clk), .rst(rst), .PC(pc_out), .Instruction(Instruction));
    assign pc = pc_out;
endmodule

Instruction Fetch/ARM.v
`include "IF_Stage.v"
`include "IF_Stage_Reg.v"
module ARM(clk, rst, freeze, flush, Branch_Tacken, Branch_Addres, PC, Instruction);
    input clk, rst, freeze, flush, Branch_Tacken;
    input [31:0] Branch_Addres;
    wire [31:0] pc, instruction;
    output [31:0] PC, Instruction;
    IF_Stage if_stage(.clk(clk), .rst(rst), .freeze(freeze), .Branch_Tacken(Branch_Tacken), .Branch_Address(Branch_Address), .pc(pc), .Instruction(instruction));
    IF_Stage_Reg if_stage_reg(.clk(clk), .rst(rst), .freeze(freeze), .flush(flush), .PC_in(pc), .Instruction_in(instruction), .PC(PC), .Instruction(Instruction));
endmodule

Instruction Fetch/ARM_TB.v
`include "ARM.v"
module ARM_TB();
	reg clk = 1'b0;
   	reg rst = 1'b0;
	reg freeze = 1'b0;
	reg Branch_Tacken = 1'b1;
    reg flush = 1'b0;
	reg [31:0] Branch_Address = 32'b00000000000000000000000000000000;
	wire [31: 0] Instruction, pc;

    ARM arm (clk, rst, freeze, flush, Branch_Tacken, Branch_Addres, PC, Instrucion);

	always #5 clk = ~clk; 
	initial begin
		$dumpfile("ARM_TB.vcd");
        $dumpvars(0, ARM_TB);
		rst = 1'b1;
		#52 rst = 1'b0; 
		#500 rst = 1'b1;
		#52 rst = 1'b0; 
		#500 $finish;
	end
endmodule

Instruction Fetch/ARM_TB.vcd
$date
	Mon Oct 30 14:26:06 2023
$end
$version
	Icarus Verilog
$end
$timescale
	1s
$end
$scope module ARM_TB $end
$var wire 1 ! PC $end
$var wire 1 " Instrucion $end
$var reg 32 # Branch_Address [31:0] $end
$var reg 1 $ Branch_Tacken $end
$var reg 1 % clk $end
$var reg 1 & flush $end
$var reg 1 ' freeze $end
$var reg 1 ( rst $end
$scope module arm $end
$var wire 32 ) Branch_Addres [31:0] $end
$var wire 1 $ Branch_Tacken $end
$var wire 1 % clk $end
$var wire 1 & flush $end
$var wire 1 ' freeze $end
$var wire 1 ( rst $end
$var wire 32 * pc [31:0] $end
$var wire 32 + instruction [31:0] $end
$var wire 32 , PC [31:0] $end
$var wire 32 - Instruction [31:0] $end
$scope module if_stage $end
$var wire 32 . Branch_Address [31:0] $end
$var wire 1 $ Branch_Tacken $end
$var wire 32 / PC_in [31:0] $end
$var wire 1 % clk $end
$var wire 1 ' freeze $end
$var wire 32 0 pc [31:0] $end
$var wire 1 ( rst $end
$var wire 32 1 pc_out [31:0] $end
$var wire 32 2 adder_o [31:0] $end
$var wire 32 3 Instruction [31:0] $end
$var reg 32 4 pc_in [31:0] $end
$scope module IM $end
$var wire 1 % clk $end
$var wire 1 ( rst $end
$var wire 32 5 PC [31:0] $end
$var reg 32 6 Instruction [31:0] $end
$upscope $end
$scope module adder_IF $end
$var wire 32 7 x1 [31:0] $end
$var wire 32 8 y [31:0] $end
$var wire 32 9 x0 [31:0] $end
$upscope $end
$scope module pc_instance $end
$var wire 1 % clk $end
$var wire 1 ' freeze $end
$var wire 32 : in [31:0] $end
$var wire 1 ( rst $end
$var reg 32 ; out [31:0] $end
$upscope $end
$upscope $end
$scope module if_stage_reg $end
$var wire 32 < Instruction_in [31:0] $end
$var wire 32 = PC_in [31:0] $end
$var wire 1 % clk $end
$var wire 1 & flush $end
$var wire 1 ' freeze $end
$var wire 1 ( rst $end
$var reg 32 > Instruction [31:0] $end
$var reg 32 ? PC [31:0] $end
$upscope $end
$upscope $end
$upscope $end
$enddefinitions $end
$comment Show the parameter values. $end
$dumpall
$end
#0
$dumpvars
b0 ?
b11100000000000000000000000000000 >
b0 =
bx <
b0 ;
bx :
b0 9
b100 8
b100 7
bx 6
b0 5
bx 4
bx 3
b100 2
b0 1
b0 0
bx /
b0z .
b11100000000000000000000000000000 -
b0 ,
bx +
b0 *
b0z )
1(
0'
0&
0%
1$
b0 #
0"
0!
$end
#5
b100 /
b100 :
b100 4
1%
#10
0%
#15
1%
#20
0%
#25
1%
#30
0%
#35
1%
#40
0%
#45
1%
#50
0%
#52
b1000100000000000000000 +
b1000100000000000000000 3
b1000100000000000000000 6
b1000100000000000000000 <
0(
#55
b11001000000000000000000 +
b11001000000000000000000 3
b11001000000000000000000 6
b11001000000000000000000 <
b1000 2
b1000 8
b100 *
b100 0
b100 =
b100 1
b100 5
b100 9
b100 ;
b1000100000000000000000 -
b1000100000000000000000 >
1%
#60
0%
#65
b101001100000000000000000 +
b101001100000000000000000 3
b101001100000000000000000 6
b101001100000000000000000 <
b100 ,
b100 ?
b11001000000000000000000 -
b11001000000000000000000 >
b1100 2
b1100 8
b1000 *
b1000 0
b1000 =
b1000 1
b1000 5
b1000 9
b1000 ;
b1000 /
b1000 :
b1000 4
1%
#70
0%
#75
b111010000001000000000000 +
b111010000001000000000000 3
b111010000001000000000000 6
b111010000001000000000000 <
b10000 2
b10000 8
b1100 *
b1100 0
b1100 =
b1100 1
b1100 5
b1100 9
b1100 ;
b1000 ,
b1000 ?
b101001100000000000000000 -
b101001100000000000000000 >
b1100 /
b1100 :
b1100 4
1%
#80
0%
#85
b1001010100001100000000000 +
b1001010100001100000000000 3
b1001010100001100000000000 6
b1001010100001100000000000 <
b1100 ,
b1100 ?
b111010000001000000000000 -
b111010000001000000000000 >
b10100 2
b10100 8
b10000 *
b10000 0
b10000 =
b10000 1
b10000 5
b10000 9
b10000 ;
b10000 /
b10000 :
b10000 4
1%
#90
0%
#95
b1011011000000000000000000 +
b1011011000000000000000000 3
b1011011000000000000000000 6
b1011011000000000000000000 <
b11000 2
b11000 8
b10100 *
b10100 0
b10100 =
b10100 1
b10100 5
b10100 9
b10100 ;
b10000 ,
b10000 ?
b1001010100001100000000000 -
b1001010100001100000000000 >
b10100 /
b10100 :
b10100 4
1%
#100
0%
#105
bx +
bx 3
bx 6
bx <
b10100 ,
b10100 ?
b1011011000000000000000000 -
b1011011000000000000000000 >
b11100 2
b11100 8
b11000 *
b11000 0
b11000 =
b11000 1
b11000 5
b11000 9
b11000 ;
b11000 /
b11000 :
b11000 4
1%
#110
0%
#115
x"
b100000 2
b100000 8
b11100 *
b11100 0
b11100 =
b11100 1
b11100 5
b11100 9
b11100 ;
b11000 ,
b11000 ?
bx -
bx >
b11100 /
b11100 :
b11100 4
1%
#120
0%
#125
b11100 ,
b11100 ?
b100100 2
b100100 8
b100000 *
b100000 0
b100000 =
b100000 1
b100000 5
b100000 9
b100000 ;
b100000 /
b100000 :
b100000 4
1%
#130
0%
#135
b101000 2
b101000 8
b100100 *
b100100 0
b100100 =
b100100 1
b100100 5
b100100 9
b100100 ;
b100000 ,
b100000 ?
b100100 /
b100100 :
b100100 4
1%
#140
0%
#145
b100100 ,
b100100 ?
b101100 2
b101100 8
b101000 *
b101000 0
b101000 =
b101000 1
b101000 5
b101000 9
b101000 ;
b101000 /
b101000 :
b101000 4
1%
#150
0%
#155
b110000 2
b110000 8
b101100 *
b101100 0
b101100 =
b101100 1
b101100 5
b101100 9
b101100 ;
b101000 ,
b101000 ?
b101100 /
b101100 :
b101100 4
1%
#160
0%
#165
b101100 ,
b101100 ?
b110100 2
b110100 8
b110000 *
b110000 0
b110000 =
b110000 1
b110000 5
b110000 9
b110000 ;
b110000 /
b110000 :
b110000 4
1%
#170
0%
#175
b111000 2
b111000 8
b110100 *
b110100 0
b110100 =
b110100 1
b110100 5
b110100 9
b110100 ;
b110000 ,
b110000 ?
b110100 /
b110100 :
b110100 4
1%
#180
0%
#185
b110100 ,
b110100 ?
b111100 2
b111100 8
b111000 *
b111000 0
b111000 =
b111000 1
b111000 5
b111000 9
b111000 ;
b111000 /
b111000 :
b111000 4
1%
#190
0%
#195
b1000000 2
b1000000 8
b111100 *
b111100 0
b111100 =
b111100 1
b111100 5
b111100 9
b111100 ;
b111000 ,
b111000 ?
b111100 /
b111100 :
b111100 4
1%
#200
0%
#205
b111100 ,
b111100 ?
b1000100 2
b1000100 8
b1000000 *
b1000000 0
b1000000 =
b1000000 1
b1000000 5
b1000000 9
b1000000 ;
b1000000 /
b1000000 :
b1000000 4
1%
#210
0%
#215
b1001000 2
b1001000 8
b1000100 *
b1000100 0
b1000100 =
b1000100 1
b1000100 5
b1000100 9
b1000100 ;
b1000000 ,
b1000000 ?
b1000100 /
b1000100 :
b1000100 4
1%
#220
0%
#225
b1000100 ,
b1000100 ?
b1001100 2
b1001100 8
b1001000 *
b1001000 0
b1001000 =
b1001000 1
b1001000 5
b1001000 9
b1001000 ;
b1001000 /
b1001000 :
b1001000 4
1%
#230
0%
#235
b1010000 2
b1010000 8
b1001100 *
b1001100 0
b1001100 =
b1001100 1
b1001100 5
b1001100 9
b1001100 ;
b1001000 ,
b1001000 ?
b1001100 /
b1001100 :
b1001100 4
1%
#240
0%
#245
b1001100 ,
b1001100 ?
b1010100 2
b1010100 8
b1010000 *
b1010000 0
b1010000 =
b1010000 1
b1010000 5
b1010000 9
b1010000 ;
b1010000 /
b1010000 :
b1010000 4
1%
#250
0%
#255
b1011000 2
b1011000 8
b1010100 *
b1010100 0
b1010100 =
b1010100 1
b1010100 5
b1010100 9
b1010100 ;
b1010000 ,
b1010000 ?
b1010100 /
b1010100 :
b1010100 4
1%
#260
0%
#265
b1010100 ,
b1010100 ?
b1011100 2
b1011100 8
b1011000 *
b1011000 0
b1011000 =
b1011000 1
b1011000 5
b1011000 9
b1011000 ;
b1011000 /
b1011000 :
b1011000 4
1%
#270
0%
#275
b1100000 2
b1100000 8
b1011100 *
b1011100 0
b1011100 =
b1011100 1
b1011100 5
b1011100 9
b1011100 ;
b1011000 ,
b1011000 ?
b1011100 /
b1011100 :
b1011100 4
1%
#280
0%
#285
b1011100 ,
b1011100 ?
b1100100 2
b1100100 8
b1100000 *
b1100000 0
b1100000 =
b1100000 1
b1100000 5
b1100000 9
b1100000 ;
b1100000 /
b1100000 :
b1100000 4
1%
#290
0%
#295
b1101000 2
b1101000 8
b1100100 *
b1100100 0
b1100100 =
b1100100 1
b1100100 5
b1100100 9
b1100100 ;
b1100000 ,
b1100000 ?
b1100100 /
b1100100 :
b1100100 4
1%
#300
0%
#305
b1100100 ,
b1100100 ?
b1101100 2
b1101100 8
b1101000 *
b1101000 0
b1101000 =
b1101000 1
b1101000 5
b1101000 9
b1101000 ;
b1101000 /
b1101000 :
b1101000 4
1%
#310
0%
#315
b1110000 2
b1110000 8
b1101100 *
b1101100 0
b1101100 =
b1101100 1
b1101100 5
b1101100 9
b1101100 ;
b1101000 ,
b1101000 ?
b1101100 /
b1101100 :
b1101100 4
1%
#320
0%
#325
b1101100 ,
b1101100 ?
b1110100 2
b1110100 8
b1110000 *
b1110000 0
b1110000 =
b1110000 1
b1110000 5
b1110000 9
b1110000 ;
b1110000 /
b1110000 :
b1110000 4
1%
#330
0%
#335
b1111000 2
b1111000 8
b1110100 *
b1110100 0
b1110100 =
b1110100 1
b1110100 5
b1110100 9
b1110100 ;
b1110000 ,
b1110000 ?
b1110100 /
b1110100 :
b1110100 4
1%
#340
0%
#345
b1110100 ,
b1110100 ?
b1111100 2
b1111100 8
b1111000 *
b1111000 0
b1111000 =
b1111000 1
b1111000 5
b1111000 9
b1111000 ;
b1111000 /
b1111000 :
b1111000 4
1%
#350
0%
#355
b10000000 2
b10000000 8
b1111100 *
b1111100 0
b1111100 =
b1111100 1
b1111100 5
b1111100 9
b1111100 ;
b1111000 ,
b1111000 ?
b1111100 /
b1111100 :
b1111100 4
1%
#360
0%
#365
b1111100 ,
b1111100 ?
b10000100 2
b10000100 8
b10000000 *
b10000000 0
b10000000 =
b10000000 1
b10000000 5
b10000000 9
b10000000 ;
b10000000 /
b10000000 :
b10000000 4
1%
#370
0%
#375
b10001000 2
b10001000 8
b10000100 *
b10000100 0
b10000100 =
b10000100 1
b10000100 5
b10000100 9
b10000100 ;
b10000000 ,
b10000000 ?
b10000100 /
b10000100 :
b10000100 4
1%
#380
0%
#385
b10000100 ,
b10000100 ?
b10001100 2
b10001100 8
b10001000 *
b10001000 0
b10001000 =
b10001000 1
b10001000 5
b10001000 9
b10001000 ;
b10001000 /
b10001000 :
b10001000 4
1%
#390
0%
#395
b10010000 2
b10010000 8
b10001100 *
b10001100 0
b10001100 =
b10001100 1
b10001100 5
b10001100 9
b10001100 ;
b10001000 ,
b10001000 ?
b10001100 /
b10001100 :
b10001100 4
1%
#400
0%
#405
b10001100 ,
b10001100 ?
b10010100 2
b10010100 8
b10010000 *
b10010000 0
b10010000 =
b10010000 1
b10010000 5
b10010000 9
b10010000 ;
b10010000 /
b10010000 :
b10010000 4
1%
#410
0%
#415
b10011000 2
b10011000 8
b10010100 *
b10010100 0
b10010100 =
b10010100 1
b10010100 5
b10010100 9
b10010100 ;
b10010000 ,
b10010000 ?
b10010100 /
b10010100 :
b10010100 4
1%
#420
0%
#425
b10010100 ,
b10010100 ?
b10011100 2
b10011100 8
b10011000 *
b10011000 0
b10011000 =
b10011000 1
b10011000 5
b10011000 9
b10011000 ;
b10011000 /
b10011000 :
b10011000 4
1%
#430
0%
#435
b10100000 2
b10100000 8
b10011100 *
b10011100 0
b10011100 =
b10011100 1
b10011100 5
b10011100 9
b10011100 ;
b10011000 ,
b10011000 ?
b10011100 /
b10011100 :
b10011100 4
1%
#440
0%
#445
b10011100 ,
b10011100 ?
b10100100 2
b10100100 8
b10100000 *
b10100000 0
b10100000 =
b10100000 1
b10100000 5
b10100000 9
b10100000 ;
b10100000 /
b10100000 :
b10100000 4
1%
#450
0%
#455
b10101000 2
b10101000 8
b10100100 *
b10100100 0
b10100100 =
b10100100 1
b10100100 5
b10100100 9
b10100100 ;
b10100000 ,
b10100000 ?
b10100100 /
b10100100 :
b10100100 4
1%
#460
0%
#465
b10100100 ,
b10100100 ?
b10101100 2
b10101100 8
b10101000 *
b10101000 0
b10101000 =
b10101000 1
b10101000 5
b10101000 9
b10101000 ;
b10101000 /
b10101000 :
b10101000 4
1%
#470
0%
#475
b10110000 2
b10110000 8
b10101100 *
b10101100 0
b10101100 =
b10101100 1
b10101100 5
b10101100 9
b10101100 ;
b10101000 ,
b10101000 ?
b10101100 /
b10101100 :
b10101100 4
1%
#480
0%
#485
b10101100 ,
b10101100 ?
b10110100 2
b10110100 8
b10110000 *
b10110000 0
b10110000 =
b10110000 1
b10110000 5
b10110000 9
b10110000 ;
b10110000 /
b10110000 :
b10110000 4
1%
#490
0%
#495
b10111000 2
b10111000 8
b10110100 *
b10110100 0
b10110100 =
b10110100 1
b10110100 5
b10110100 9
b10110100 ;
b10110000 ,
b10110000 ?
b10110100 /
b10110100 :
b10110100 4
1%
#500
0%
#505
b10110100 ,
b10110100 ?
b10111100 2
b10111100 8
b10111000 *
b10111000 0
b10111000 =
b10111000 1
b10111000 5
b10111000 9
b10111000 ;
b10111000 /
b10111000 :
b10111000 4
1%
#510
0%
#515
b11000000 2
b11000000 8
b10111100 *
b10111100 0
b10111100 =
b10111100 1
b10111100 5
b10111100 9
b10111100 ;
b10111000 ,
b10111000 ?
b10111100 /
b10111100 :
b10111100 4
1%
#520
0%
#525
b10111100 ,
b10111100 ?
b11000100 2
b11000100 8
b11000000 *
b11000000 0
b11000000 =
b11000000 1
b11000000 5
b11000000 9
b11000000 ;
b11000000 /
b11000000 :
b11000000 4
1%
#530
0%
#535
b11001000 2
b11001000 8
b11000100 *
b11000100 0
b11000100 =
b11000100 1
b11000100 5
b11000100 9
b11000100 ;
b11000000 ,
b11000000 ?
b11000100 /
b11000100 :
b11000100 4
1%
#540
0%
#545
b11000100 ,
b11000100 ?
b11001100 2
b11001100 8
b11001000 *
b11001000 0
b11001000 =
b11001000 1
b11001000 5
b11001000 9
b11001000 ;
b11001000 /
b11001000 :
b11001000 4
1%
#550
0%
#552
0"
b100 2
b100 8
b0 *
b0 0
b0 =
b0 1
b0 5
b0 9
b0 ;
b11100000000000000000000000000000 -
b11100000000000000000000000000000 >
b0 ,
b0 ?
1(
#555
b100 /
b100 :
b100 4
1%
#560
0%
#565
1%
#570
0%
#575
1%
#580
0%
#585
1%
#590
0%
#595
1%
#600
0%
#604
b1000100000000000000000 +
b1000100000000000000000 3
b1000100000000000000000 6
b1000100000000000000000 <
0(
#605
b11001000000000000000000 +
b11001000000000000000000 3
b11001000000000000000000 6
b11001000000000000000000 <
b1000 2
b1000 8
b100 *
b100 0
b100 =
b100 1
b100 5
b100 9
b100 ;
b1000100000000000000000 -
b1000100000000000000000 >
1%
#610
0%
#615
b101001100000000000000000 +
b101001100000000000000000 3
b101001100000000000000000 6
b101001100000000000000000 <
b100 ,
b100 ?
b11001000000000000000000 -
b11001000000000000000000 >
b1100 2
b1100 8
b1000 *
b1000 0
b1000 =
b1000 1
b1000 5
b1000 9
b1000 ;
b1000 /
b1000 :
b1000 4
1%
#620
0%
#625
b111010000001000000000000 +
b111010000001000000000000 3
b111010000001000000000000 6
b111010000001000000000000 <
b10000 2
b10000 8
b1100 *
b1100 0
b1100 =
b1100 1
b1100 5
b1100 9
b1100 ;
b1000 ,
b1000 ?
b101001100000000000000000 -
b101001100000000000000000 >
b1100 /
b1100 :
b1100 4
1%
#630
0%
#635
b1001010100001100000000000 +
b1001010100001100000000000 3
b1001010100001100000000000 6
b1001010100001100000000000 <
b1100 ,
b1100 ?
b111010000001000000000000 -
b111010000001000000000000 >
b10100 2
b10100 8
b10000 *
b10000 0
b10000 =
b10000 1
b10000 5
b10000 9
b10000 ;
b10000 /
b10000 :
b10000 4
1%
#640
0%
#645
b1011011000000000000000000 +
b1011011000000000000000000 3
b1011011000000000000000000 6
b1011011000000000000000000 <
b11000 2
b11000 8
b10100 *
b10100 0
b10100 =
b10100 1
b10100 5
b10100 9
b10100 ;
b10000 ,
b10000 ?
b1001010100001100000000000 -
b1001010100001100000000000 >
b10100 /
b10100 :
b10100 4
1%
#650
0%
#655
bx +
bx 3
bx 6
bx <
b10100 ,
b10100 ?
b1011011000000000000000000 -
b1011011000000000000000000 >
b11100 2
b11100 8
b11000 *
b11000 0
b11000 =
b11000 1
b11000 5
b11000 9
b11000 ;
b11000 /
b11000 :
b11000 4
1%
#660
0%
#665
x"
b100000 2
b100000 8
b11100 *
b11100 0
b11100 =
b11100 1
b11100 5
b11100 9
b11100 ;
b11000 ,
b11000 ?
bx -
bx >
b11100 /
b11100 :
b11100 4
1%
#670
0%
#675
b11100 ,
b11100 ?
b100100 2
b100100 8
b100000 *
b100000 0
b100000 =
b100000 1
b100000 5
b100000 9
b100000 ;
b100000 /
b100000 :
b100000 4
1%
#680
0%
#685
b101000 2
b101000 8
b100100 *
b100100 0
b100100 =
b100100 1
b100100 5
b100100 9
b100100 ;
b100000 ,
b100000 ?
b100100 /
b100100 :
b100100 4
1%
#690
0%
#695
b100100 ,
b100100 ?
b101100 2
b101100 8
b101000 *
b101000 0
b101000 =
b101000 1
b101000 5
b101000 9
b101000 ;
b101000 /
b101000 :
b101000 4
1%
#700
0%
#705
b110000 2
b110000 8
b101100 *
b101100 0
b101100 =
b101100 1
b101100 5
b101100 9
b101100 ;
b101000 ,
b101000 ?
b101100 /
b101100 :
b101100 4
1%
#710
0%
#715
b101100 ,
b101100 ?
b110100 2
b110100 8
b110000 *
b110000 0
b110000 =
b110000 1
b110000 5
b110000 9
b110000 ;
b110000 /
b110000 :
b110000 4
1%
#720
0%
#725
b111000 2
b111000 8
b110100 *
b110100 0
b110100 =
b110100 1
b110100 5
b110100 9
b110100 ;
b110000 ,
b110000 ?
b110100 /
b110100 :
b110100 4
1%
#730
0%
#735
b110100 ,
b110100 ?
b111100 2
b111100 8
b111000 *
b111000 0
b111000 =
b111000 1
b111000 5
b111000 9
b111000 ;
b111000 /
b111000 :
b111000 4
1%
#740
0%
#745
b1000000 2
b1000000 8
b111100 *
b111100 0
b111100 =
b111100 1
b111100 5
b111100 9
b111100 ;
b111000 ,
b111000 ?
b111100 /
b111100 :
b111100 4
1%
#750
0%
#755
b111100 ,
b111100 ?
b1000100 2
b1000100 8
b1000000 *
b1000000 0
b1000000 =
b1000000 1
b1000000 5
b1000000 9
b1000000 ;
b1000000 /
b1000000 :
b1000000 4
1%
#760
0%
#765
b1001000 2
b1001000 8
b1000100 *
b1000100 0
b1000100 =
b1000100 1
b1000100 5
b1000100 9
b1000100 ;
b1000000 ,
b1000000 ?
b1000100 /
b1000100 :
b1000100 4
1%
#770
0%
#775
b1000100 ,
b1000100 ?
b1001100 2
b1001100 8
b1001000 *
b1001000 0
b1001000 =
b1001000 1
b1001000 5
b1001000 9
b1001000 ;
b1001000 /
b1001000 :
b1001000 4
1%
#780
0%
#785
b1010000 2
b1010000 8
b1001100 *
b1001100 0
b1001100 =
b1001100 1
b1001100 5
b1001100 9
b1001100 ;
b1001000 ,
b1001000 ?
b1001100 /
b1001100 :
b1001100 4
1%
#790
0%
#795
b1001100 ,
b1001100 ?
b1010100 2
b1010100 8
b1010000 *
b1010000 0
b1010000 =
b1010000 1
b1010000 5
b1010000 9
b1010000 ;
b1010000 /
b1010000 :
b1010000 4
1%
#800
0%
#805
b1011000 2
b1011000 8
b1010100 *
b1010100 0
b1010100 =
b1010100 1
b1010100 5
b1010100 9
b1010100 ;
b1010000 ,
b1010000 ?
b1010100 /
b1010100 :
b1010100 4
1%
#810
0%
