Instruction Fetch/PC.v
module PC(clk, rst, freeze, in, out);
input clk, rst, freeze;
input [31:0] in;
output reg [31:0] out;
  always @ (posedge clk, posedge rst) begin
    if (rst) out <= 32'b0;
    else begin
      if (freeze) out <= out;
      else out <= in;
    end
  end

endmodule

Instruction Fetch/PC_tb.v
module PC_tb();
    reg clk, rst, freeze;
    reg [31:0] in;
    wire [31:0] out;
    always #10 clk = ~clk;
    initial begin
        $dumpfile("PC.vcd");
        $dumpvars(0, pc);
        $monitor("PC input is %d, and PC output is %d.", in, out);
        clk = 1'b0;
        rst = 1'b1;
        in = 32'd25;
        #25 rst = 1'b0;
        #55 in = 32'd1001;
        #55 freeze = 1'b1;
        #55 in = 32'd503;
        #55 freeze = 1'b0;
        #100 $finish;

    end
    PC pc(.clk(clk), .rst(rst), .freeze(freeze), .in(in), .out(out));
endmodule

Instruction Fetch/PC.vcd
$date
	Mon Oct 16 14:49:22 2023
$end
$version
	Icarus Verilog
$end
$timescale
	1s
$end
$scope module PC_tb $end
$scope module pc $end
$var wire 1 ! clk $end
$var wire 1 " freeze $end
$var wire 32 # in [31:0] $end
$var wire 1 $ rst $end
$var reg 32 % out [31:0] $end
$upscope $end
$upscope $end
$enddefinitions $end
$comment Show the parameter values. $end
$dumpall
$end
#0
$dumpvars
b0 %
1$
b11001 #
x"
0!
$end
#10
1!
#20
0!
#25
0$
#30
b11001 %
1!
#40
0!
#50
1!
#60
0!
#70
1!
#80
0!
b1111101001 #
#90
b1111101001 %
1!
#100
0!
#110
1!
#120
0!
#130
1!
#135
1"
#140
0!
#150
1!
#160
0!
#170
1!
#180
0!
#190
1!
b111110111 #
#200
0!
#210
1!
#220
0!
#230
1!
#240
0!
#245
0"
#250
b111110111 %
1!
