debugged_ARM/EXE_STAGE/stage_IF_to_ID_register.v
module Stage_IF_to_ID_Register(
    input clk, rst, freeze, flush,
    input [31:0] pc_in, instruction_in,
    output reg [31:0] pc_out, instruction_out
);
    always @(posedge clk, posedge rst) begin
        if(rst) begin
            pc_out <= 32'd0;
            instruction_out <= 32'd0;
        end
        else if (flush) begin
            pc_out <= 32'd0;
            instruction_out <= 32'd0;
        end
        else if (~freeze) begin
            pc_out <= pc_in;
            instruction_out <= instruction_in;
        end
    end
endmodule

debugged_ARM/IF_STAGE/mux_2to1.v
module MUX_2to1 #(parameter N = 32)(
    input [N-1:0] x0, x1,
    input sel,
    output [N-1:0] res
);
    assign res = sel ? x1 : x0;
endmodule

debugged_ARM/IF_STAGE/instruction_memory.v

module Instruction_memory(
    input clk, rst, 
    input [31:0]PC, 
    output reg [31:0]Instruction
    );

    reg [7:0] _Instruction[191:0];

    always @ (*) begin
        if (rst) begin
            {_Instruction[3],  _Instruction[2],  _Instruction[1],  _Instruction[0]} =  32'b1110_00_1_1101_0_0000_0000_000000010100; //MOV R0 ,#20 //R0 = 20          -> R0 = 20
            {_Instruction[7],  _Instruction[6],  _Instruction[5],  _Instruction[4]} =  32'b1110_00_1_1101_0_0000_0001_101000000001; //MOV R1 ,#4096          -> R1 = 4096
            {_Instruction[11],  _Instruction[10],  _Instruction[9], _Instruction[8]} = 332'b1110_00_1_1101_0_0000_0010_000100000011; //MOV R2 ,#0xC0000000 //R2 = -1073741824
            {_Instruction[15], _Instruction[14], _Instruction[13], _Instruction[12]} = 32'b1110_00_0_0100_1_0010_0011_000000000010; //ADDS R3 ,R2,R2 //R3 = -2147483648 
            {_Instruction[19], _Instruction[18], _Instruction[17], _Instruction[16]} = 32'b1110_00_0_0101_0_0000_0100_000000000000; //ADC R4 ,R0,R0 //R4 = 41
            {_Instruction[23], _Instruction[22], _Instruction[21], _Instruction[20]} = 32'b1110_00_0_0010_0_0100_0101_000100000100; //SUB R5 ,R4,R4,LSL #2 //R5 = -123
            {_Instruction[27], _Instruction[26], _Instruction[25], _Instruction[24]} = 32'b1110_00_0_0110_0_0000_0110_000010100000; //SBC R6 ,R0,R0,LSR #1 //R6 = 10
            {_Instruction[31], _Instruction[30], _Instruction[29], _Instruction[28]} = 32'b1110_00_0_1100_0_0101_0111_000101000010; //ORR R7 ,R5,R2,ASR #2 //R7 = -123
            {_Instruction[35], _Instruction[34], _Instruction[33], _Instruction[32]} = 32'b1110_00_0_0000_0_0111_1000_000000000011; //AND R8 ,R7,R3 //R8 = -2147483648
            {_Instruction[39], _Instruction[38], _Instruction[37], _Instruction[36]} = 32'b1110_00_0_1111_0_0000_1001_000000000110; //MVN R9 ,R6 //R9 = -11
            {_Instruction[43], _Instruction[42], _Instruction[41], _Instruction[40]} = 32'b1110_00_0_0001_0_0100_1010_000000000101; //EOR R10,R4,R5 //R10 = -84
            {_Instruction[47], _Instruction[46], _Instruction[45], _Instruction[44]} = 32'b1110_00_0_1010_1_1000_0000_000000000110; //CMP R8 ,R6
            {_Instruction[51], _Instruction[50], _Instruction[49], _Instruction[48]} = 32'b0001_00_0_0100_0_0001_0001_000000000001; //ADDNE R1 ,R1,R1 //R1 = 8192
            {_Instruction[55], _Instruction[54], _Instruction[53], _Instruction[52]} = 32'b1110_00_0_1000_1_1001_0000_000000001000; //TST R9 ,R8
            {_Instruction[59], _Instruction[58], _Instruction[57], _Instruction[56]} = 32'b0000_00_0_0100_0_0010_0010_000000000010; //ADDEQ R2 ,R2,R2 //R2 = -1073741824
            {_Instruction[63], _Instruction[62], _Instruction[61], _Instruction[60]} = 32'b1110_00_1_1101_0_0000_0000_101100000001; //MOV R0 ,#1024 //R0 = 1024
            {_Instruction[67], _Instruction[66], _Instruction[65], _Instruction[64]} = 32'b1110_01_0_0100_0_0000_0001_000000000000; //STR R1 ,[R0],#0 //MEM[1024] = 8192
            {_Instruction[71], _Instruction[70], _Instruction[69], _Instruction[68]} = 32'b1110_01_0_0100_1_0000_1011_000000000000; //LDR R11,[R0],#0 //R11 = 8192
            {_Instruction[75], _Instruction[74], _Instruction[73], _Instruction[72]} = 32'b1110_01_0_0100_0_0000_0010_000000000100; //STR R2 ,[R0],#4 //MEM[1028] = -1073741824
            {_Instruction[79], _Instruction[78], _Instruction[77], _Instruction[76]} = 32'b1110_01_0_0100_0_0000_0011_000000001000; //STR R3 ,[R0],#8 //MEM[1032] = -2147483648
            {_Instruction[83], _Instruction[82], _Instruction[81], _Instruction[80]} = 32'b1110_01_0_0100_0_0000_0100_000000001101; //STR R4 ,[R0],#13 //MEM[1036] = 41
            {_Instruction[87], _Instruction[86], _Instruction[85], _Instruction[84]} = 32'b1110_01_0_0100_0_0000_0101_000000010000; //STR R5 ,[R0],#16 //MEM[1040] = -123
            {_Instruction[91], _Instruction[90], _Instruction[89], _Instruction[88]} = 32'b1110_01_0_0100_0_0000_0110_000000010100; //STR R6 ,[R0],#20 //MEM[1044] = 10
            {_Instruction[95], _Instruction[94], _Instruction[93], _Instruction[92]} = 32'b1110_01_0_0100_1_0000_1010_000000000100; //LDR R10,[R0],#4 //R10 = -1073741824
            {_Instruction[99],  _Instruction[98],  _Instruction[97], _Instruction[96]} = 32'b1110_01_0_0100_0_0000_0111_000000011000; //STR R7 ,[R0],#24 //MEM[1048] = -123
            {_Instruction[103], _Instruction[102], _Instruction[101], _Instruction[100]} = 32'b1110_00_1_1101_0_0000_0001_000000000100; //MOV R1 ,#4 //R1 = 4
            {_Instruction[107], _Instruction[106], _Instruction[105], _Instruction[104]} = 32'b1110_00_1_1101_0_0000_0010_000000000000; //MOV R2 ,#0 //R2 = 0
            {_Instruction[111], _Instruction[110], _Instruction[109], _Instruction[108]} = 32'b1110_00_1_1101_0_0000_0011_000000000000; //MOV R3 ,#0 //R3 = 0
            {_Instruction[115], _Instruction[114], _Instruction[113], _Instruction[112]} =  32'b1110_00_0_0100_0_0000_0100_000100000011; //ADD R4 ,R0,R3,LSL #2
            {_Instruction[119], _Instruction[118], _Instruction[117], _Instruction[116]} = 32'b1110_01_0_0100_1_0100_0101_000000000000; //LDR R5 ,[R4],#0
            {_Instruction[123], _Instruction[122], _Instruction[121], _Instruction[120]} = 32'b1110_01_0_0100_1_0100_0110_000000000100; //LDR R6 ,[R4],#4
            {_Instruction[127], _Instruction[126], _Instruction[125], _Instruction[124]} = 32'b1110_00_0_1010_1_0101_0000_000000000110; //CMP R5 ,R6
            {_Instruction[131], _Instruction[130], _Instruction[129], _Instruction[128]} = 32'b1100_01_0_0100_0_0100_0110_000000000000; //STRGT R6 ,[R4],#0
            {_Instruction[135], _Instruction[134], _Instruction[133], _Instruction[132]} = 32'b1100_01_0_0100_0_0100_0101_000000000100; //STRGT R5 ,[R4],#4
            {_Instruction[139], _Instruction[138], _Instruction[137], _Instruction[136]} = 32'b1110_00_1_0100_0_0011_0011_000000000001; //ADD R3 ,R3,#1
            {_Instruction[143], _Instruction[142], _Instruction[141], _Instruction[140]} = 32'b1110_00_1_1010_1_0011_0000_000000000011; //CMP R3 ,#3
            {_Instruction[147], _Instruction[146], _Instruction[145], _Instruction[144]} = 32'b1011_10_1_0_111111111111111111110111 ; //BLT #-9
            {_Instruction[151], _Instruction[150], _Instruction[149], _Instruction[148]} = 32'b1110_00_1_0100_0_0010_0010_000000000001; //ADD R2 ,R2,#1
            {_Instruction[155], _Instruction[154], _Instruction[153], _Instruction[152]} = 32'b1110_00_0_1010_1_0010_0000_000000000001; //CMP R2 ,R1
            {_Instruction[159], _Instruction[158], _Instruction[157], _Instruction[156]} = 32'b1011_10_1_0_111111111111111111110011 ; //BLT #-13
            {_Instruction[163], _Instruction[162], _Instruction[161], _Instruction[160]} = 32'b1110_01_0_0100_1_0000_0001_000000000000; //LDR R1 ,[R0],#0 //R1 = -2147483648
            {_Instruction[167], _Instruction[166], _Instruction[165], _Instruction[164]} = 32'b1110_01_0_0100_1_0000_0010_000000000100; //LDR R2 ,[R0],#4 //R2 = -1073741824
            {_Instruction[171], _Instruction[170], _Instruction[169], _Instruction[168]} = 32'b1110_01_0_0100_1_0000_0011_000000001000; //LDR R3 ,[R0],#8 //R3 = 41
            {_Instruction[175], _Instruction[174], _Instruction[173], _Instruction[172]} = 32'b1110_01_0_0100_1_0000_0100_000000001100; //LDR R4 ,[R0],#12 //R4 = 8192
            {_Instruction[179], _Instruction[178], _Instruction[177], _Instruction[176]} = 32'b1110_01_0_0100_1_0000_0101_000000010000; //LDR R5 ,[R0],#16 //R5 = -123
            {_Instruction[183], _Instruction[182], _Instruction[181], _Instruction[180]} = 32'b1110_01_0_0100_1_0000_0110_000000010100; //LDR R6 ,[R0],#20 //R6 = 10
            {_Instruction[187], _Instruction[186], _Instruction[185], _Instruction[184]} = 32'b1110_10_1_0_111111111111111111111111 ; //B #-1
            {_Instruction[191], _Instruction[190], _Instruction[189], _Instruction[188]} = 32'd0;
        end else Instruction <= {_Instruction[PC + 2'b11], _Instruction[PC + 2'b10], _Instruction[PC + 2'b01], _Instruction[PC + 2'b00]};  
  end
    
endmodule

debugged_ARM/ID_STAGE/adder.v
module Adder(
	input [31:0] x0, x1,
	output [31:0] res
);
	assign res = x0 + x1;
endmodule

debugged_ARM/ID_STAGE/pc.v
module PC(
    input clk, rst, freeze,
    input [31:0] in,
    output reg [31:0] out
);
  always @ (posedge clk, posedge rst) begin
    if (rst) out <= 32'b0;
    else begin
      if (freeze) out <= out;
      else out <= in;
    end
  end

endmodule

debugged_ARM/IF_STAGE/stage_IF.v
`include "mux_2to1.v"
`include "adder.v"
`include "pc.v"
`include "instruction_memory.v"
module Stage_IF (
    input clk, rst, freeze, Branch_taken,
    input [31:0] BranchAddr,
    output [31:0] PC, Instruction
);
    wire [31:0] pc_reg_in, pc_reg_out, pc_adder_out;
    assign PC = pc_adder_out;
    PC pc(
        .clk(clk),
        .rst(rst),
        .freeze(freeze),
        .in(pc_reg_in),
        .out(pc_reg_out)
    );
    Adder adder(
        .x0(pc_reg_out),
        .x1(32'd4),
        .res(pc_adder_out)

    );
    Instruction_memory instruction_memory(
    .clk(clk),
    .rst(rst), 
    .PC(pc_reg_out), 
    .Instruction(Instruction)
    );
    MUX_2to1 mux(
        .x0(pc_adder_out),
        .x1(BranchAddr),
        .sel(Branch_taken),
        .res(pc_reg_in)
    );

endmodule

debugged_ARM/IF_STAGE/ARM.v
`include "stage_IF.v"
`include "stage_IF_to_ID_register.v"
module ARM(
    input clk, rst
);
    // IF
    wire hazard, Branch_taken;
    assign hazard = 1'b0, Branch_taken = 1'b0, BranchAddr_if_stage_in = 32'd0; //remove it later
    wire [31:0] BranchAddr_if_stage_in;
    wire [31:0] PC_if_stage_out, Instruction_if_stage_out;
    Stage_IF stage_if(
        .clk(clk),
        .rst(rst),
        .freeze(hazard),
        .Branch_taken(Branch_taken),
        .BranchAddr(BranchAddr_if_stage_in),
        .PC(PC_if_stage_out),
        .Instruction(Instruction_if_stage_out)
    );
    // IF Register
    wire [31:0] PC_if_to_id_register_out, instruction_if_to_id_register_out;
    Stage_IF_to_ID_Register stage_if_to_id_register(
    .clk(clk), 
    .rst(rst),
    .freeze(hazard), 
    .flush(Branch_taken),
    .pc_in(PC_if_stage_out), 
    .instruction_in(Instruction_if_stage_out),
    .pc_out(PC_if_to_id_register_out),
    .instruction_out(instruction_if_to_id_register_out)
);
endmodule

debugged_ARM/IF_STAGE/ARM_TB.v
`timescale 1ns/1ns
`include "ARM.v"
module ARM_TB();
    localparam HCLK = 5;

    reg clk, rst;

    ARM arm(clk, rst);

    always #HCLK clk = ~clk;

    initial begin
        $dumpfile("ARM_TB.vcd");
        $dumpvars(0, ARM_TB);
        {clk, rst} = 2'b01;
        #10 rst = 1'b0;
        #3000 $finish;
    end
endmodule

debugged_ARM/IF_STAGE/ARM_TB.vcd
$date
	Wed Dec 20 12:35:38 2023
$end
$version
	Icarus Verilog
$end
$timescale
	1ns
$end
$scope module ARM_TB $end
$var parameter 32 ! HCLK $end
$var reg 1 " clk $end
$var reg 1 # rst $end
$scope module arm $end
$var wire 32 $ BranchAddr_if_stage_in [31:0] $end
$var wire 1 % Branch_taken $end
$var wire 1 " clk $end
$var wire 1 & hazard $end
$var wire 1 # rst $end
$var wire 32 ' instruction_if_to_id_register_out [31:0] $end
$var wire 32 ( PC_if_to_id_register_out [31:0] $end
$var wire 32 ) PC_if_stage_out [31:0] $end
$var wire 32 * Instruction_if_stage_out [31:0] $end
$scope module stage_if $end
$var wire 32 + BranchAddr [31:0] $end
$var wire 1 % Branch_taken $end
$var wire 32 , PC [31:0] $end
$var wire 1 " clk $end
$var wire 1 & freeze $end
$var wire 1 # rst $end
$var wire 32 - pc_reg_out [31:0] $end
$var wire 32 . pc_reg_in [31:0] $end
$var wire 32 / pc_adder_out [31:0] $end
$var wire 32 0 Instruction [31:0] $end
$scope module adder $end
$var wire 32 1 x1 [31:0] $end
$var wire 32 2 x0 [31:0] $end
$var wire 32 3 res [31:0] $end
$upscope $end
$scope module instruction_memory $end
$var wire 1 " clk $end
$var wire 1 # rst $end
$var wire 32 4 PC [31:0] $end
$var reg 32 5 Instruction [31:0] $end
$upscope $end
$scope module mux $end
$var wire 32 6 res [31:0] $end
$var wire 1 % sel $end
$var wire 32 7 x0 [31:0] $end
$var wire 32 8 x1 [31:0] $end
$var parameter 32 9 N $end
$upscope $end
$scope module pc $end
$var wire 1 " clk $end
$var wire 1 & freeze $end
$var wire 32 : in [31:0] $end
$var wire 1 # rst $end
$var reg 32 ; out [31:0] $end
$upscope $end
$upscope $end
$scope module stage_if_to_id_register $end
$var wire 1 " clk $end
$var wire 1 % flush $end
$var wire 1 & freeze $end
$var wire 32 < instruction_in [31:0] $end
$var wire 32 = pc_in [31:0] $end
$var wire 1 # rst $end
$var reg 32 > instruction_out [31:0] $end
$var reg 32 ? pc_out [31:0] $end
$upscope $end
$upscope $end
$upscope $end
$enddefinitions $end
$comment Show the parameter values. $end
$dumpall
b100000 9
b101 !
$end
#0
$dumpvars
b0 ?
b0 >
b100 =
bx <
b0 ;
b100 :
b0 8
b100 7
b100 6
bx 5
b0 4
b100 3
b0 2
b100 1
bx 0
b100 /
b100 .
b0 -
b100 ,
b0 +
bx *
b100 )
b0 (
b0 '
0&
0%
b0 $
1#
0"
$end
#5
1"
#10
b11100011101000000000000000010100 *
b11100011101000000000000000010100 0
b11100011101000000000000000010100 5
b11100011101000000000000000010100 <
0"
0#
#15
b11100011101000000001101000000001 *
b11100011101000000001101000000001 0
b11100011101000000001101000000001 5
b11100011101000000001101000000001 <
b1000 .
b1000 6
b1000 :
b1000 )
b1000 ,
b1000 =
b1000 /
b1000 3
b1000 7
b100 -
b100 2
b100 4
b100 ;
b11100011101000000000000000010100 '
b11100011101000000000000000010100 >
b100 (
b100 ?
1"
#20
0"
#25
b11100011101000000010000100000011 *
b11100011101000000010000100000011 0
b11100011101000000010000100000011 5
b11100011101000000010000100000011 <
b11100011101000000001101000000001 '
b11100011101000000001101000000001 >
b1000 (
b1000 ?
b1100 .
b1100 6
b1100 :
b1100 )
b1100 ,
b1100 =
b1100 /
b1100 3
b1100 7
b1000 -
b1000 2
b1000 4
b1000 ;
1"
#30
0"
#35
b11100000100100100011000000000010 *
b11100000100100100011000000000010 0
b11100000100100100011000000000010 5
b11100000100100100011000000000010 <
b10000 .
b10000 6
b10000 :
b10000 )
b10000 ,
b10000 =
b10000 /
b10000 3
b10000 7
b1100 -
b1100 2
b1100 4
b1100 ;
b11100011101000000010000100000011 '
b11100011101000000010000100000011 >
b1100 (
b1100 ?
1"
#40
0"
#45
b11100000101000000100000000000000 *
b11100000101000000100000000000000 0
b11100000101000000100000000000000 5
b11100000101000000100000000000000 <
b11100000100100100011000000000010 '
b11100000100100100011000000000010 >
b10000 (
b10000 ?
b10100 .
b10100 6
b10100 :
b10100 )
b10100 ,
b10100 =
b10100 /
b10100 3
b10100 7
b10000 -
b10000 2
b10000 4
b10000 ;
1"
#50
0"
#55
b11100000010001000101000100000100 *
b11100000010001000101000100000100 0
b11100000010001000101000100000100 5
b11100000010001000101000100000100 <
b11000 .
b11000 6
b11000 :
b11000 )
b11000 ,
b11000 =
b11000 /
b11000 3
b11000 7
b10100 -
b10100 2
b10100 4
b10100 ;
b11100000101000000100000000000000 '
b11100000101000000100000000000000 >
b10100 (
b10100 ?
1"
#60
0"
#65
b11100000110000000110000010100000 *
b11100000110000000110000010100000 0
b11100000110000000110000010100000 5
b11100000110000000110000010100000 <
b11100000010001000101000100000100 '
b11100000010001000101000100000100 >
b11000 (
b11000 ?
b11100 .
b11100 6
b11100 :
b11100 )
b11100 ,
b11100 =
b11100 /
b11100 3
b11100 7
b11000 -
b11000 2
b11000 4
b11000 ;
1"
#70
0"
#75
b11100001100001010111000101000010 *
b11100001100001010111000101000010 0
b11100001100001010111000101000010 5
b11100001100001010111000101000010 <
b100000 .
b100000 6
b100000 :
b100000 )
b100000 ,
b100000 =
b100000 /
b100000 3
b100000 7
b11100 -
b11100 2
b11100 4
b11100 ;
b11100000110000000110000010100000 '
b11100000110000000110000010100000 >
b11100 (
b11100 ?
1"
#80
0"
#85
b11100000000001111000000000000011 *
b11100000000001111000000000000011 0
b11100000000001111000000000000011 5
b11100000000001111000000000000011 <
b11100001100001010111000101000010 '
b11100001100001010111000101000010 >
b100000 (
b100000 ?
b100100 .
b100100 6
b100100 :
b100100 )
b100100 ,
b100100 =
b100100 /
b100100 3
b100100 7
b100000 -
b100000 2
b100000 4
b100000 ;
1"
#90
0"
#95
b11100001111000001001000000000110 *
b11100001111000001001000000000110 0
b11100001111000001001000000000110 5
b11100001111000001001000000000110 <
b101000 .
b101000 6
b101000 :
b101000 )
b101000 ,
b101000 =
b101000 /
b101000 3
b101000 7
b100100 -
b100100 2
b100100 4
b100100 ;
b11100000000001111000000000000011 '
b11100000000001111000000000000011 >
b100100 (
b100100 ?
1"
#100
0"
#105
b11100000001001001010000000000101 *
b11100000001001001010000000000101 0
b11100000001001001010000000000101 5
b11100000001001001010000000000101 <
b11100001111000001001000000000110 '
b11100001111000001001000000000110 >
b101000 (
b101000 ?
b101100 .
b101100 6
b101100 :
b101100 )
b101100 ,
b101100 =
b101100 /
b101100 3
b101100 7
b101000 -
b101000 2
b101000 4
b101000 ;
1"
#110
0"
#115
b11100001010110000000000000000110 *
b11100001010110000000000000000110 0
b11100001010110000000000000000110 5
b11100001010110000000000000000110 <
b110000 .
b110000 6
b110000 :
b110000 )
b110000 ,
b110000 =
b110000 /
b110000 3
b110000 7
b101100 -
b101100 2
b101100 4
b101100 ;
b11100000001001001010000000000101 '
b11100000001001001010000000000101 >
b101100 (
b101100 ?
1"
#120
0"
#125
b10000100000010001000000000001 *
b10000100000010001000000000001 0
b10000100000010001000000000001 5
b10000100000010001000000000001 <
b11100001010110000000000000000110 '
b11100001010110000000000000000110 >
b110000 (
b110000 ?
b110100 .
b110100 6
b110100 :
b110100 )
b110100 ,
b110100 =
b110100 /
b110100 3
b110100 7
b110000 -
b110000 2
b110000 4
b110000 ;
1"
#130
0"
#135
b11100001000110010000000000001000 *
b11100001000110010000000000001000 0
b11100001000110010000000000001000 5
b11100001000110010000000000001000 <
b111000 .
b111000 6
b111000 :
b111000 )
b111000 ,
b111000 =
b111000 /
b111000 3
b111000 7
b110100 -
b110100 2
b110100 4
b110100 ;
b10000100000010001000000000001 '
b10000100000010001000000000001 >
b110100 (
b110100 ?
1"
#140
0"
#145
b100000100010000000000010 *
b100000100010000000000010 0
b100000100010000000000010 5
b100000100010000000000010 <
b11100001000110010000000000001000 '
b11100001000110010000000000001000 >
b111000 (
b111000 ?
b111100 .
b111100 6
b111100 :
b111100 )
b111100 ,
b111100 =
b111100 /
b111100 3
b111100 7
b111000 -
b111000 2
b111000 4
b111000 ;
1"
#150
0"
#155
b11100011101000000000101100000001 *
b11100011101000000000101100000001 0
b11100011101000000000101100000001 5
b11100011101000000000101100000001 <
b1000000 .
b1000000 6
b1000000 :
b1000000 )
b1000000 ,
b1000000 =
b1000000 /
b1000000 3
b1000000 7
b111100 -
b111100 2
b111100 4
b111100 ;
b100000100010000000000010 '
b100000100010000000000010 >
b111100 (
b111100 ?
1"
#160
0"
#165
b11100100100000000001000000000000 *
b11100100100000000001000000000000 0
b11100100100000000001000000000000 5
b11100100100000000001000000000000 <
b11100011101000000000101100000001 '
b11100011101000000000101100000001 >
b1000000 (
b1000000 ?
b1000100 .
b1000100 6
b1000100 :
b1000100 )
b1000100 ,
b1000100 =
b1000100 /
b1000100 3
b1000100 7
b1000000 -
b1000000 2
b1000000 4
b1000000 ;
1"
#170
0"
#175
b11100100100100001011000000000000 *
b11100100100100001011000000000000 0
b11100100100100001011000000000000 5
b11100100100100001011000000000000 <
b1001000 .
b1001000 6
b1001000 :
b1001000 )
b1001000 ,
b1001000 =
b1001000 /
b1001000 3
b1001000 7
b1000100 -
b1000100 2
b1000100 4
b1000100 ;
b11100100100000000001000000000000 '
b11100100100000000001000000000000 >
b1000100 (
b1000100 ?
1"
#180
0"
#185
b11100100100000000010000000000100 *
b11100100100000000010000000000100 0
b11100100100000000010000000000100 5
b11100100100000000010000000000100 <
b11100100100100001011000000000000 '
b11100100100100001011000000000000 >
b1001000 (
b1001000 ?
b1001100 .
b1001100 6
b1001100 :
b1001100 )
b1001100 ,
b1001100 =
b1001100 /
b1001100 3
b1001100 7
b1001000 -
b1001000 2
b1001000 4
b1001000 ;
1"
#190
0"
#195
b11100100100000000011000000001000 *
b11100100100000000011000000001000 0
b11100100100000000011000000001000 5
b11100100100000000011000000001000 <
b1010000 .
b1010000 6
b1010000 :
b1010000 )
b1010000 ,
b1010000 =
b1010000 /
b1010000 3
b1010000 7
b1001100 -
b1001100 2
b1001100 4
b1001100 ;
b11100100100000000010000000000100 '
b11100100100000000010000000000100 >
b1001100 (
b1001100 ?
1"
#200
0"
#205
b11100100100000000100000000001101 *
b11100100100000000100000000001101 0
b11100100100000000100000000001101 5
b11100100100000000100000000001101 <
b11100100100000000011000000001000 '
b11100100100000000011000000001000 >
b1010000 (
b1010000 ?
b1010100 .
b1010100 6
b1010100 :
b1010100 )
b1010100 ,
b1010100 =
b1010100 /
b1010100 3
b1010100 7
b1010000 -
b1010000 2
b1010000 4
b1010000 ;
1"
#210
0"
#215
b11100100100000000101000000010000 *
b11100100100000000101000000010000 0
b11100100100000000101000000010000 5
b11100100100000000101000000010000 <
b1011000 .
b1011000 6
b1011000 :
b1011000 )
b1011000 ,
b1011000 =
b1011000 /
b1011000 3
b1011000 7
b1010100 -
b1010100 2
b1010100 4
b1010100 ;
b11100100100000000100000000001101 '
b11100100100000000100000000001101 >
b1010100 (
b1010100 ?
1"
#220
0"
#225
b11100100100000000110000000010100 *
b11100100100000000110000000010100 0
b11100100100000000110000000010100 5
b11100100100000000110000000010100 <
b11100100100000000101000000010000 '
b11100100100000000101000000010000 >
b1011000 (
b1011000 ?
b1011100 .
b1011100 6
b1011100 :
b1011100 )
b1011100 ,
b1011100 =
b1011100 /
b1011100 3
b1011100 7
b1011000 -
b1011000 2
b1011000 4
b1011000 ;
1"
#230
0"
#235
b11100100100100001010000000000100 *
b11100100100100001010000000000100 0
b11100100100100001010000000000100 5
b11100100100100001010000000000100 <
b1100000 .
b1100000 6
b1100000 :
b1100000 )
b1100000 ,
b1100000 =
b1100000 /
b1100000 3
b1100000 7
b1011100 -
b1011100 2
b1011100 4
b1011100 ;
b11100100100000000110000000010100 '
b11100100100000000110000000010100 >
b1011100 (
b1011100 ?
1"
#240
0"
#245
b11100100100000000111000000011000 *
b11100100100000000111000000011000 0
b11100100100000000111000000011000 5
b11100100100000000111000000011000 <
b11100100100100001010000000000100 '
b11100100100100001010000000000100 >
b1100000 (
b1100000 ?
b1100100 .
b1100100 6
b1100100 :
b1100100 )
b1100100 ,
b1100100 =
b1100100 /
b1100100 3
b1100100 7
b1100000 -
b1100000 2
b1100000 4
b1100000 ;
1"
#250
0"
#255
b11100011101000000001000000000100 *
b11100011101000000001000000000100 0
b11100011101000000001000000000100 5
b11100011101000000001000000000100 <
b1101000 .
b1101000 6
b1101000 :
b1101000 )
b1101000 ,
b1101000 =
b1101000 /
b1101000 3
b1101000 7
b1100100 -
b1100100 2
b1100100 4
b1100100 ;
b11100100100000000111000000011000 '
b11100100100000000111000000011000 >
b1100100 (
b1100100 ?
1"
#260
0"
#265
b11100011101000000010000000000000 *
b11100011101000000010000000000000 0
b11100011101000000010000000000000 5
b11100011101000000010000000000000 <
b11100011101000000001000000000100 '
b11100011101000000001000000000100 >
b1101000 (
b1101000 ?
b1101100 .
b1101100 6
b1101100 :
b1101100 )
b1101100 ,
b1101100 =
b1101100 /
b1101100 3
b1101100 7
b1101000 -
b1101000 2
b1101000 4
b1101000 ;
1"
#270
0"
#275
b11100011101000000011000000000000 *
b11100011101000000011000000000000 0
b11100011101000000011000000000000 5
b11100011101000000011000000000000 <
b1110000 .
b1110000 6
b1110000 :
b1110000 )
b1110000 ,
b1110000 =
b1110000 /
b1110000 3
b1110000 7
b1101100 -
b1101100 2
b1101100 4
b1101100 ;
b11100011101000000010000000000000 '
b11100011101000000010000000000000 >
b1101100 (
b1101100 ?
1"
#280
0"
#285
b11100000100000000100000100000011 *
b11100000100000000100000100000011 0
b11100000100000000100000100000011 5
b11100000100000000100000100000011 <
b11100011101000000011000000000000 '
b11100011101000000011000000000000 >
b1110000 (
b1110000 ?
b1110100 .
b1110100 6
b1110100 :
b1110100 )
b1110100 ,
b1110100 =
b1110100 /
b1110100 3
b1110100 7
b1110000 -
b1110000 2
b1110000 4
b1110000 ;
1"
#290
0"
#295
b11100100100101000101000000000000 *
b11100100100101000101000000000000 0
b11100100100101000101000000000000 5
b11100100100101000101000000000000 <
b1111000 .
b1111000 6
b1111000 :
b1111000 )
b1111000 ,
b1111000 =
b1111000 /
b1111000 3
b1111000 7
b1110100 -
b1110100 2
b1110100 4
b1110100 ;
b11100000100000000100000100000011 '
b11100000100000000100000100000011 >
b1110100 (
b1110100 ?
1"
#300
0"
#305
b11100100100101000110000000000100 *
b11100100100101000110000000000100 0
b11100100100101000110000000000100 5
b11100100100101000110000000000100 <
b11100100100101000101000000000000 '
b11100100100101000101000000000000 >
b1111000 (
b1111000 ?
b1111100 .
b1111100 6
b1111100 :
b1111100 )
b1111100 ,
b1111100 =
b1111100 /
b1111100 3
b1111100 7
b1111000 -
b1111000 2
b1111000 4
b1111000 ;
1"
#310
0"
#315
b11100001010101010000000000000110 *
b11100001010101010000000000000110 0
b11100001010101010000000000000110 5
b11100001010101010000000000000110 <
b10000000 .
b10000000 6
b10000000 :
b10000000 )
b10000000 ,
b10000000 =
b10000000 /
b10000000 3
b10000000 7
b1111100 -
b1111100 2
b1111100 4
b1111100 ;
b11100100100101000110000000000100 '
b11100100100101000110000000000100 >
b1111100 (
b1111100 ?
1"
#320
0"
#325
b11000100100001000110000000000000 *
b11000100100001000110000000000000 0
b11000100100001000110000000000000 5
b11000100100001000110000000000000 <
b11100001010101010000000000000110 '
b11100001010101010000000000000110 >
b10000000 (
b10000000 ?
b10000100 .
b10000100 6
b10000100 :
b10000100 )
b10000100 ,
b10000100 =
b10000100 /
b10000100 3
b10000100 7
b10000000 -
b10000000 2
b10000000 4
b10000000 ;
1"
#330
0"
#335
b11000100100001000101000000000100 *
b11000100100001000101000000000100 0
b11000100100001000101000000000100 5
b11000100100001000101000000000100 <
b10001000 .
b10001000 6
b10001000 :
b10001000 )
b10001000 ,
b10001000 =
b10001000 /
b10001000 3
b10001000 7
b10000100 -
b10000100 2
b10000100 4
b10000100 ;
b11000100100001000110000000000000 '
b11000100100001000110000000000000 >
b10000100 (
b10000100 ?
1"
#340
0"
#345
b11100010100000110011000000000001 *
b11100010100000110011000000000001 0
b11100010100000110011000000000001 5
b11100010100000110011000000000001 <
b11000100100001000101000000000100 '
b11000100100001000101000000000100 >
b10001000 (
b10001000 ?
b10001100 .
b10001100 6
b10001100 :
b10001100 )
b10001100 ,
b10001100 =
b10001100 /
b10001100 3
b10001100 7
b10001000 -
b10001000 2
b10001000 4
b10001000 ;
1"
#350
0"
#355
b11100011010100110000000000000011 *
b11100011010100110000000000000011 0
b11100011010100110000000000000011 5
b11100011010100110000000000000011 <
b10010000 .
b10010000 6
b10010000 :
b10010000 )
b10010000 ,
b10010000 =
b10010000 /
b10010000 3
b10010000 7
b10001100 -
b10001100 2
b10001100 4
b10001100 ;
b11100010100000110011000000000001 '
b11100010100000110011000000000001 >
b10001100 (
b10001100 ?
1"
#360
0"
#365
b10111010111111111111111111110111 *
b10111010111111111111111111110111 0
b10111010111111111111111111110111 5
b10111010111111111111111111110111 <
b11100011010100110000000000000011 '
b11100011010100110000000000000011 >
b10010000 (
b10010000 ?
b10010100 .
b10010100 6
b10010100 :
b10010100 )
b10010100 ,
b10010100 =
b10010100 /
b10010100 3
b10010100 7
b10010000 -
b10010000 2
b10010000 4
b10010000 ;
1"
#370
0"
#375
b11100010100000100010000000000001 *
b11100010100000100010000000000001 0
b11100010100000100010000000000001 5
b11100010100000100010000000000001 <
b10011000 .
b10011000 6
b10011000 :
b10011000 )
b10011000 ,
b10011000 =
b10011000 /
b10011000 3
b10011000 7
b10010100 -
b10010100 2
b10010100 4
b10010100 ;
b10111010111111111111111111110111 '
b10111010111111111111111111110111 >
b10010100 (
b10010100 ?
1"
#380
0"
